ardiss/GPModel.py
ardiss/__init__.py
ardiss/ard_computation.py
ardiss/ard_model.py
ardiss/ardiss_transform.py
ardiss/classes.py
ardiss/data_io.py
ardiss/data_loading.py
ardiss/experiment_classes.py
ardiss/imputation_model.py
ardiss/impute_ard.py
ardiss/scripts.py
ardiss/utilities.py
ardiss-0.1.3.dist-info/DESCRIPTION.rst
ardiss-0.1.3.dist-info/METADATA
ardiss-0.1.3.dist-info/RECORD
ardiss-0.1.3.dist-info/WHEEL
ardiss-0.1.3.dist-info/entry_points.txt
ardiss-0.1.3.dist-info/metadata.json
ardiss-0.1.3.dist-info/top_level.txt
